windmolen/__init__.py
windmolen/api.py
windmolen-0.0.1.dist-info/LICENSE
windmolen-0.0.1.dist-info/METADATA
windmolen-0.0.1.dist-info/WHEEL
windmolen-0.0.1.dist-info/top_level.txt
windmolen-0.0.1.dist-info/RECORD
