Metadata-Version: 2.1
Name: windmolen
Version: 0.0.1
Summary: Treat multiple async iterators as a single async iterator.
Author-email: Austin Raney <aaraney@protonmail.com>
License: MIT License
Keywords: async,iterator
Classifier: Development Status :: 3 - Alpha
Classifier: Intended Audience :: Developers
Classifier: License :: OSI Approved :: MIT License
Classifier: Operating System :: Microsoft :: Windows
Classifier: Operating System :: Unix
Classifier: Programming Language :: Python :: 3.7
Classifier: Programming Language :: Python :: 3.8
Classifier: Programming Language :: Python :: 3.9
Classifier: Programming Language :: Python :: 3.10
Classifier: Programming Language :: Python :: 3.11
Classifier: Topic :: Utilities
Requires-Python: >=3.7
License-File: LICENSE
Requires-Dist: typing-extensions
Provides-Extra: dev
Requires-Dist: black ; extra == 'dev'
Provides-Extra: test
Requires-Dist: pytest (>=7.0.0) ; extra == 'test'
Requires-Dist: pytest-asyncio ; extra == 'test'
